qiskit_qir/__init__.py
qiskit_qir/capability.py
qiskit_qir/elements.py
qiskit_qir/translate.py
qiskit_qir/visitor.py
qiskit_qir_alice_bob_fork-0.5.0.dist-info/licenses/LICENSE
qiskit_qir_alice_bob_fork-0.5.0.dist-info/licenses/NOTICE.txt
qiskit_qir_alice_bob_fork-0.5.0.dist-info/METADATA
qiskit_qir_alice_bob_fork-0.5.0.dist-info/WHEEL
qiskit_qir_alice_bob_fork-0.5.0.dist-info/top_level.txt
qiskit_qir_alice_bob_fork-0.5.0.dist-info/RECORD
