Metadata-Version: 2.4
Name: qiskit-qir-alice-bob-fork
Version: 0.5.0
Summary: Qiskit to QIR translator
Home-page: https://github.com/Alice-Bob-SW/qiskit-qir
Author: Alice & Bob
Author-email: contact@alice-bob.com
Project-URL: Bug Tracker, https://github.com/Alice-Bob-SW/qiskit-qir
Classifier: Development Status :: 3 - Alpha
Classifier: Intended Audience :: Developers
Classifier: License :: OSI Approved :: MIT License
Classifier: Natural Language :: English
Classifier: Programming Language :: Python :: 3
Classifier: Programming Language :: Python :: 3.8
Classifier: Programming Language :: Python :: 3.9
Classifier: Programming Language :: Python :: 3.10
Classifier: Programming Language :: Python :: 3.11
Classifier: Programming Language :: Python :: 3.12
Classifier: Operating System :: Microsoft
Classifier: Operating System :: MacOS
Classifier: Operating System :: Unix
Requires-Python: >=3.8
License-File: LICENSE
License-File: NOTICE.txt
Requires-Dist: qiskit<2.0,>=1.0.0
Requires-Dist: pyqir<0.11.0,>=0.10.0
Provides-Extra: test
Requires-Dist: pytest; extra == "test"
Dynamic: license-file
